{"width":25,"height":20,"cells":[[{"x":0,"y":0,"isVisible":false,"type":"WALL"},{"x":0,"y":1,"isVisible":false,"type":"WALL"},{"x":0,"y":2,"isVisible":false,"type":"WALL"},{"x":0,"y":3,"isVisible":false,"type":"WALL"},{"x":0,"y":4,"isVisible":false,"type":"WALL"},{"x":0,"y":5,"isVisible":false,"type":"WALL"},{"x":0,"y":6,"isVisible":false,"type":"WALL"},{"x":0,"y":7,"isVisible":false,"type":"WALL"},{"x":0,"y":8,"isVisible":true,"type":"WALL"},{"x":0,"y":9,"isVisible":true,"type":"EMPTY"},{"x":0,"y":10,"isVisible":true,"type":"EMPTY"},{"x":0,"y":11,"isVisible":true,"type":"EMPTY"},{"x":0,"y":12,"isVisible":true,"type":"EMPTY"},{"x":0,"y":13,"isVisible":true,"type":"EMPTY"},{"x":0,"y":14,"isVisible":true,"type":"EMPTY"},{"x":0,"y":15,"isVisible":true,"type":"EMPTY"},{"x":0,"y":16,"isVisible":true,"type":"EMPTY"},{"x":0,"y":17,"isVisible":true,"type":"EMPTY"},{"x":0,"y":18,"isVisible":true,"type":"EMPTY"},{"x":0,"y":19,"isVisible":true,"type":"EMPTY"}],[{"x":1,"y":0,"isVisible":false,"type":"WALL"},{"x":1,"y":1,"isVisible":false,"type":"FLOOR"},{"x":1,"y":2,"isVisible":false,"type":"FLOOR"},{"x":1,"y":3,"isVisible":false,"type":"FLOOR"},{"x":1,"y":4,"isVisible":false,"type":"FLOOR"},{"x":1,"y":5,"isVisible":false,"type":"FLOOR"},{"x":1,"y":6,"isVisible":false,"type":"FLOOR"},{"x":1,"y":7,"isVisible":false,"type":"FLOOR"},{"x":1,"y":8,"isVisible":true,"type":"WALL"},{"x":1,"y":9,"isVisible":true,"type":"DECORATION0"},{"x":1,"y":10,"isVisible":true,"type":"EMPTY"},{"x":1,"y":11,"isVisible":true,"type":"EMPTY"},{"x":1,"y":12,"isVisible":true,"type":"EMPTY"},{"x":1,"y":13,"isVisible":true,"type":"EMPTY"},{"x":1,"y":14,"isVisible":true,"type":"EMPTY"},{"x":1,"y":15,"isVisible":true,"type":"EMPTY"},{"x":1,"y":16,"isVisible":true,"type":"EMPTY"},{"x":1,"y":17,"isVisible":true,"type":"EMPTY"},{"x":1,"y":18,"isVisible":true,"type":"EMPTY"},{"x":1,"y":19,"isVisible":true,"type":"EMPTY"}],[{"x":2,"y":0,"isVisible":false,"type":"WALL"},{"x":2,"y":1,"isVisible":false,"type":"FLOOR","actor":{"random":{"seed":160076455110889,"nextNextGaussian":0.0,"haveNextNextGaussian":false},"health":30,"attack":5,"defence":0}},{"x":2,"y":2,"isVisible":false,"type":"FLOOR"},{"x":2,"y":3,"isVisible":false,"type":"FLOOR"},{"x":2,"y":4,"isVisible":false,"type":"FLOOR"},{"x":2,"y":5,"isVisible":false,"type":"FLOOR"},{"x":2,"y":6,"isVisible":false,"type":"FLOOR"},{"x":2,"y":7,"isVisible":false,"type":"FLOOR"},{"x":2,"y":8,"isVisible":true,"type":"WALL"},{"x":2,"y":9,"isVisible":true,"type":"EMPTY"},{"x":2,"y":10,"isVisible":true,"type":"EMPTY"},{"x":2,"y":11,"isVisible":true,"type":"EMPTY"},{"x":2,"y":12,"isVisible":true,"type":"WALL"},{"x":2,"y":13,"isVisible":true,"type":"WALL"},{"x":2,"y":14,"isVisible":true,"type":"WALL"},{"x":2,"y":15,"isVisible":true,"type":"WALL"},{"x":2,"y":16,"isVisible":true,"type":"WALL"},{"x":2,"y":17,"isVisible":true,"type":"WALL"},{"x":2,"y":18,"isVisible":true,"type":"WALL"},{"x":2,"y":19,"isVisible":true,"type":"WALL"}],[{"x":3,"y":0,"isVisible":false,"type":"WALL"},{"x":3,"y":1,"isVisible":false,"type":"FLOOR"},{"x":3,"y":2,"isVisible":false,"type":"FLOOR"},{"x":3,"y":3,"isVisible":false,"type":"FLOOR"},{"x":3,"y":4,"isVisible":false,"type":"FLOOR"},{"x":3,"y":5,"isVisible":false,"type":"FLOOR"},{"x":3,"y":6,"isVisible":false,"type":"FLOOR"},{"x":3,"y":7,"isVisible":false,"type":"FLOOR"},{"x":3,"y":8,"isVisible":true,"type":"WALL"},{"x":3,"y":9,"isVisible":true,"type":"EMPTY"},{"x":3,"y":10,"isVisible":true,"type":"EMPTY"},{"x":3,"y":11,"isVisible":true,"type":"EMPTY"},{"x":3,"y":12,"isVisible":true,"type":"WALL"},{"x":3,"y":13,"isVisible":true,"type":"FLOOR"},{"x":3,"y":14,"isVisible":true,"type":"FLOOR"},{"x":3,"y":15,"isVisible":true,"type":"FLOOR"},{"x":3,"y":16,"isVisible":true,"type":"FLOOR"},{"x":3,"y":17,"isVisible":true,"type":"FLOOR"},{"x":3,"y":18,"isVisible":true,"type":"FLOOR"},{"x":3,"y":19,"isVisible":true,"type":"WALL"}],[{"x":4,"y":0,"isVisible":false,"type":"WALL"},{"x":4,"y":1,"isVisible":false,"type":"FLOOR"},{"x":4,"y":2,"isVisible":false,"type":"FLOOR"},{"x":4,"y":3,"isVisible":false,"type":"FLOOR"},{"x":4,"y":4,"isVisible":false,"type":"FLOOR"},{"x":4,"y":5,"isVisible":false,"type":"FLOOR"},{"x":4,"y":6,"isVisible":false,"type":"FLOOR"},{"x":4,"y":7,"isVisible":false,"type":"FLOOR"},{"x":4,"y":8,"isVisible":true,"type":"WALL"},{"x":4,"y":9,"isVisible":true,"type":"WALL"},{"x":4,"y":10,"isVisible":true,"type":"WALL"},{"x":4,"y":11,"isVisible":true,"type":"WALL"},{"x":4,"y":12,"isVisible":true,"type":"WALL"},{"x":4,"y":13,"isVisible":true,"type":"FLOOR"},{"x":4,"y":14,"isVisible":true,"type":"FLOOR"},{"x":4,"y":15,"isVisible":true,"type":"FLOOR"},{"x":4,"y":16,"isVisible":true,"type":"FLOOR"},{"x":4,"y":17,"isVisible":true,"type":"FLOOR"},{"x":4,"y":18,"isVisible":true,"type":"FLOOR"},{"x":4,"y":19,"isVisible":true,"type":"WALL"}],[{"x":5,"y":0,"isVisible":false,"type":"WALL"},{"x":5,"y":1,"isVisible":false,"type":"FLOOR"},{"x":5,"y":2,"isVisible":false,"type":"FLOOR"},{"x":5,"y":3,"isVisible":false,"type":"FLOOR"},{"x":5,"y":4,"isVisible":false,"type":"FLOOR"},{"x":5,"y":5,"isVisible":false,"type":"FLOOR"},{"x":5,"y":6,"isVisible":false,"type":"FLOOR"},{"x":5,"y":7,"isVisible":false,"type":"FLOOR"},{"x":5,"y":8,"isVisible":true,"type":"FLOOR"},{"x":5,"y":9,"isVisible":true,"type":"FLOOR"},{"x":5,"y":10,"isVisible":true,"type":"FLOOR"},{"x":5,"y":11,"isVisible":true,"type":"FLOOR"},{"x":5,"y":12,"isVisible":true,"type":"FLOOR"},{"x":5,"y":13,"isVisible":true,"type":"FLOOR"},{"x":5,"y":14,"isVisible":true,"type":"FLOOR"},{"x":5,"y":15,"isVisible":true,"type":"FLOOR"},{"x":5,"y":16,"isVisible":true,"type":"FLOOR"},{"x":5,"y":17,"isVisible":true,"type":"FLOOR"},{"x":5,"y":18,"isVisible":true,"type":"FLOOR"},{"x":5,"y":19,"isVisible":true,"type":"WALL"}],[{"x":6,"y":0,"isVisible":false,"type":"WALL"},{"x":6,"y":1,"isVisible":false,"type":"FLOOR"},{"x":6,"y":2,"isVisible":false,"type":"FLOOR"},{"x":6,"y":3,"isVisible":false,"type":"FLOOR"},{"x":6,"y":4,"isVisible":false,"type":"FLOOR"},{"x":6,"y":5,"isVisible":false,"type":"FLOOR"},{"x":6,"y":6,"isVisible":false,"type":"FLOOR"},{"x":6,"y":7,"isVisible":false,"type":"FLOOR"},{"x":6,"y":8,"isVisible":true,"type":"FLOOR"},{"x":6,"y":9,"isVisible":true,"type":"FLOOR"},{"x":6,"y":10,"isVisible":true,"type":"FLOOR"},{"x":6,"y":11,"isVisible":true,"type":"FLOOR"},{"x":6,"y":12,"isVisible":true,"type":"FLOOR"},{"x":6,"y":13,"isVisible":true,"type":"FLOOR"},{"x":6,"y":14,"isVisible":true,"type":"FLOOR"},{"x":6,"y":15,"isVisible":true,"type":"FLOOR"},{"x":6,"y":16,"isVisible":true,"type":"FLOOR"},{"x":6,"y":17,"isVisible":true,"type":"FLOOR"},{"x":6,"y":18,"isVisible":true,"type":"FLOOR"},{"x":6,"y":19,"isVisible":true,"type":"WALL"}],[{"x":7,"y":0,"isVisible":false,"type":"WALL"},{"x":7,"y":1,"isVisible":false,"type":"FLOOR"},{"x":7,"y":2,"isVisible":false,"type":"FLOOR","actor":{"random":{"seed":96989281652537,"nextNextGaussian":0.0,"haveNextNextGaussian":false},"health":30,"attack":5,"defence":0}},{"x":7,"y":3,"isVisible":false,"type":"FLOOR"},{"x":7,"y":4,"isVisible":false,"type":"FLOOR"},{"x":7,"y":5,"isVisible":false,"type":"FLOOR"},{"x":7,"y":6,"isVisible":false,"type":"FLOOR"},{"x":7,"y":7,"isVisible":false,"type":"FLOOR","actor":{"random":{"seed":153550337362109,"nextNextGaussian":0.0,"haveNextNextGaussian":false},"health":30,"attack":5,"defence":0}},{"x":7,"y":8,"isVisible":true,"type":"WALL"},{"x":7,"y":9,"isVisible":true,"type":"WALL"},{"x":7,"y":10,"isVisible":true,"type":"WALL"},{"x":7,"y":11,"isVisible":true,"type":"WALL"},{"x":7,"y":12,"isVisible":true,"type":"WALL"},{"x":7,"y":13,"isVisible":true,"type":"FLOOR"},{"x":7,"y":14,"isVisible":true,"type":"KEY","item":{"type":"KEY"}},{"x":7,"y":15,"isVisible":true,"type":"FLOOR"},{"x":7,"y":16,"isVisible":true,"type":"FLOOR"},{"x":7,"y":17,"isVisible":true,"type":"FLOOR"},{"x":7,"y":18,"isVisible":true,"type":"FLOOR","actor":{"inventory":{"items":[{"type":"POTION"},{"attack":5,"type":"SWORD"}]},"random":{"seed":214698845793437,"nextNextGaussian":0.0,"haveNextNextGaussian":false},"health":300,"attack":20,"defence":0}},{"x":7,"y":19,"isVisible":true,"type":"WALL"}],[{"x":8,"y":0,"isVisible":false,"type":"WALL"},{"x":8,"y":1,"isVisible":false,"type":"FLOOR"},{"x":8,"y":2,"isVisible":false,"type":"FLOOR"},{"x":8,"y":3,"isVisible":false,"type":"FLOOR"},{"x":8,"y":4,"isVisible":false,"type":"FLOOR"},{"x":8,"y":5,"isVisible":false,"type":"FLOOR"},{"x":8,"y":6,"isVisible":false,"type":"FLOOR"},{"x":8,"y":7,"isVisible":false,"type":"FLOOR"},{"x":8,"y":8,"isVisible":true,"type":"WALL"},{"x":8,"y":9,"isVisible":true,"type":"EMPTY"},{"x":8,"y":10,"isVisible":true,"type":"EMPTY"},{"x":8,"y":11,"isVisible":true,"type":"EMPTY"},{"x":8,"y":12,"isVisible":true,"type":"WALL"},{"x":8,"y":13,"isVisible":true,"type":"FLOOR"},{"x":8,"y":14,"isVisible":true,"type":"FLOOR"},{"x":8,"y":15,"isVisible":true,"type":"FLOOR"},{"x":8,"y":16,"isVisible":true,"type":"FLOOR"},{"x":8,"y":17,"isVisible":true,"type":"FLOOR"},{"x":8,"y":18,"isVisible":true,"type":"FLOOR"},{"x":8,"y":19,"isVisible":true,"type":"WALL"}],[{"x":9,"y":0,"isVisible":false,"type":"WALL"},{"x":9,"y":1,"isVisible":false,"type":"FLOOR"},{"x":9,"y":2,"isVisible":false,"type":"FLOOR"},{"x":9,"y":3,"isVisible":false,"type":"FLOOR"},{"x":9,"y":4,"isVisible":false,"type":"FLOOR"},{"x":9,"y":5,"isVisible":false,"type":"FLOOR"},{"x":9,"y":6,"isVisible":false,"type":"FLOOR"},{"x":9,"y":7,"isVisible":false,"type":"FLOOR"},{"x":9,"y":8,"isVisible":true,"type":"WALL"},{"x":9,"y":9,"isVisible":true,"type":"EMPTY"},{"x":9,"y":10,"isVisible":true,"type":"EMPTY"},{"x":9,"y":11,"isVisible":true,"type":"EMPTY"},{"x":9,"y":12,"isVisible":true,"type":"WALL"},{"x":9,"y":13,"isVisible":true,"type":"FLOOR"},{"x":9,"y":14,"isVisible":true,"type":"FLOOR"},{"x":9,"y":15,"isVisible":true,"type":"FLOOR"},{"x":9,"y":16,"isVisible":true,"type":"FLOOR"},{"x":9,"y":17,"isVisible":true,"type":"FLOOR"},{"x":9,"y":18,"isVisible":true,"type":"FLOOR"},{"x":9,"y":19,"isVisible":true,"type":"WALL"}],[{"x":10,"y":0,"isVisible":false,"type":"WALL"},{"x":10,"y":1,"isVisible":false,"type":"FLOOR"},{"x":10,"y":2,"isVisible":false,"type":"FLOOR"},{"x":10,"y":3,"isVisible":false,"type":"FLOOR"},{"x":10,"y":4,"isVisible":false,"type":"FLOOR"},{"x":10,"y":5,"isVisible":false,"type":"FLOOR"},{"x":10,"y":6,"isVisible":false,"type":"FLOOR"},{"x":10,"y":7,"isVisible":false,"type":"FLOOR"},{"x":10,"y":8,"isVisible":true,"type":"WALL"},{"x":10,"y":9,"isVisible":true,"type":"DECORATION13"},{"x":10,"y":10,"isVisible":true,"type":"EMPTY"},{"x":10,"y":11,"isVisible":true,"type":"EMPTY"},{"x":10,"y":12,"isVisible":true,"type":"WALL"},{"x":10,"y":13,"isVisible":true,"type":"WALL"},{"x":10,"y":14,"isVisible":true,"type":"WALL"},{"x":10,"y":15,"isVisible":true,"type":"WALL"},{"x":10,"y":16,"isVisible":true,"type":"WALL"},{"x":10,"y":17,"isVisible":true,"type":"WALL"},{"x":10,"y":18,"isVisible":true,"type":"WALL"},{"x":10,"y":19,"isVisible":true,"type":"WALL"}],[{"x":11,"y":0,"isVisible":false,"type":"WALL"},{"x":11,"y":1,"isVisible":false,"type":"FLOOR"},{"x":11,"y":2,"isVisible":false,"type":"FLOOR"},{"x":11,"y":3,"isVisible":false,"type":"FLOOR"},{"x":11,"y":4,"isVisible":false,"type":"FLOOR"},{"x":11,"y":5,"isVisible":false,"type":"FLOOR"},{"x":11,"y":6,"isVisible":false,"type":"FLOOR"},{"x":11,"y":7,"isVisible":false,"type":"FLOOR"},{"x":11,"y":8,"isVisible":false,"type":"WALL"},{"x":11,"y":9,"isVisible":false,"type":"EMPTY"},{"x":11,"y":10,"isVisible":false,"type":"EMPTY"},{"x":11,"y":11,"isVisible":false,"type":"EMPTY"},{"x":11,"y":12,"isVisible":false,"type":"EMPTY"},{"x":11,"y":13,"isVisible":true,"type":"EMPTY"},{"x":11,"y":14,"isVisible":true,"type":"EMPTY"},{"x":11,"y":15,"isVisible":true,"type":"EMPTY"},{"x":11,"y":16,"isVisible":true,"type":"EMPTY"},{"x":11,"y":17,"isVisible":true,"type":"EMPTY"},{"x":11,"y":18,"isVisible":true,"type":"EMPTY"},{"x":11,"y":19,"isVisible":true,"type":"EMPTY"}],[{"x":12,"y":0,"isVisible":false,"type":"WALL","actor":{"teleportCountdown":3,"random":{"seed":256824330668289,"nextNextGaussian":0.0,"haveNextNextGaussian":false},"health":999,"attack":20,"defence":999}},{"x":12,"y":1,"isVisible":false,"type":"WALL"},{"x":12,"y":2,"isVisible":false,"type":"WALL"},{"x":12,"y":3,"isVisible":false,"type":"FLOOR"},{"x":12,"y":4,"isVisible":false,"type":"WALL"},{"x":12,"y":5,"isVisible":false,"type":"WALL"},{"x":12,"y":6,"isVisible":false,"type":"WALL"},{"x":12,"y":7,"isVisible":false,"type":"WALL"},{"x":12,"y":8,"isVisible":false,"type":"WALL"},{"x":12,"y":9,"isVisible":false,"type":"DECORATION21"},{"x":12,"y":10,"isVisible":false,"type":"EMPTY"},{"x":12,"y":11,"isVisible":false,"type":"EMPTY"},{"x":12,"y":12,"isVisible":false,"type":"EMPTY"},{"x":12,"y":13,"isVisible":true,"type":"EMPTY"},{"x":12,"y":14,"isVisible":true,"type":"DECORATION6"},{"x":12,"y":15,"isVisible":true,"type":"EMPTY"},{"x":12,"y":16,"isVisible":true,"type":"EMPTY"},{"x":12,"y":17,"isVisible":true,"type":"EMPTY"},{"x":12,"y":18,"isVisible":true,"type":"EMPTY"},{"x":12,"y":19,"isVisible":true,"type":"EMPTY"}],[{"x":13,"y":0,"isVisible":false,"type":"EMPTY"},{"x":13,"y":1,"isVisible":false,"type":"EMPTY"},{"x":13,"y":2,"isVisible":false,"type":"WALL"},{"x":13,"y":3,"isVisible":false,"type":"FLOOR"},{"x":13,"y":4,"isVisible":false,"type":"WALL"},{"x":13,"y":5,"isVisible":false,"type":"DECORATION4"},{"x":13,"y":6,"isVisible":false,"type":"EMPTY"},{"x":13,"y":7,"isVisible":false,"type":"EMPTY"},{"x":13,"y":8,"isVisible":false,"type":"EMPTY"},{"x":13,"y":9,"isVisible":false,"type":"EMPTY"},{"x":13,"y":10,"isVisible":false,"type":"EMPTY"},{"x":13,"y":11,"isVisible":false,"type":"EMPTY"},{"x":13,"y":12,"isVisible":false,"type":"EMPTY"},{"x":13,"y":13,"isVisible":false,"type":"EMPTY"},{"x":13,"y":14,"isVisible":false,"type":"EMPTY"},{"x":13,"y":15,"isVisible":false,"type":"EMPTY"},{"x":13,"y":16,"isVisible":false,"type":"EMPTY"},{"x":13,"y":17,"isVisible":false,"type":"DECORATION17"},{"x":13,"y":18,"isVisible":false,"type":"EMPTY"},{"x":13,"y":19,"isVisible":false,"type":"EMPTY"}],[{"x":14,"y":0,"isVisible":false,"type":"EMPTY"},{"x":14,"y":1,"isVisible":false,"type":"DECORATION3"},{"x":14,"y":2,"isVisible":false,"type":"WALL"},{"x":14,"y":3,"isVisible":false,"type":"FLOOR"},{"x":14,"y":4,"isVisible":false,"type":"WALL"},{"x":14,"y":5,"isVisible":false,"type":"EMPTY"},{"x":14,"y":6,"isVisible":false,"type":"EMPTY"},{"x":14,"y":7,"isVisible":false,"type":"EMPTY"},{"x":14,"y":8,"isVisible":false,"type":"EMPTY"},{"x":14,"y":9,"isVisible":false,"type":"EMPTY"},{"x":14,"y":10,"isVisible":false,"type":"EMPTY"},{"x":14,"y":11,"isVisible":false,"type":"EMPTY"},{"x":14,"y":12,"isVisible":false,"type":"DECORATION12"},{"x":14,"y":13,"isVisible":false,"type":"EMPTY"},{"x":14,"y":14,"isVisible":false,"type":"EMPTY"},{"x":14,"y":15,"isVisible":false,"type":"EMPTY"},{"x":14,"y":16,"isVisible":false,"type":"EMPTY"},{"x":14,"y":17,"isVisible":false,"type":"DECORATION0"},{"x":14,"y":18,"isVisible":false,"type":"EMPTY"},{"x":14,"y":19,"isVisible":false,"type":"EMPTY"}],[{"x":15,"y":0,"isVisible":false,"type":"DECORATION13"},{"x":15,"y":1,"isVisible":false,"type":"EMPTY"},{"x":15,"y":2,"isVisible":false,"type":"WALL"},{"x":15,"y":3,"isVisible":false,"type":"FLOOR"},{"x":15,"y":4,"isVisible":false,"type":"WALL"},{"x":15,"y":5,"isVisible":false,"type":"EMPTY"},{"x":15,"y":6,"isVisible":false,"type":"EMPTY"},{"x":15,"y":7,"isVisible":false,"type":"EMPTY"},{"x":15,"y":8,"isVisible":false,"type":"EMPTY"},{"x":15,"y":9,"isVisible":false,"type":"EMPTY"},{"x":15,"y":10,"isVisible":false,"type":"EMPTY"},{"x":15,"y":11,"isVisible":false,"type":"EMPTY"},{"x":15,"y":12,"isVisible":false,"type":"EMPTY"},{"x":15,"y":13,"isVisible":false,"type":"EMPTY"},{"x":15,"y":14,"isVisible":false,"type":"EMPTY"},{"x":15,"y":15,"isVisible":false,"type":"EMPTY"},{"x":15,"y":16,"isVisible":false,"type":"EMPTY"},{"x":15,"y":17,"isVisible":false,"type":"EMPTY"},{"x":15,"y":18,"isVisible":false,"type":"EMPTY"},{"x":15,"y":19,"isVisible":false,"type":"DECORATION16"}],[{"x":16,"y":0,"isVisible":false,"type":"EMPTY"},{"x":16,"y":1,"isVisible":false,"type":"EMPTY"},{"x":16,"y":2,"isVisible":false,"type":"WALL"},{"x":16,"y":3,"isVisible":false,"type":"FLOOR"},{"x":16,"y":4,"isVisible":false,"type":"WALL"},{"x":16,"y":5,"isVisible":false,"type":"EMPTY"},{"x":16,"y":6,"isVisible":false,"type":"EMPTY"},{"x":16,"y":7,"isVisible":false,"type":"EMPTY"},{"x":16,"y":8,"isVisible":false,"type":"EMPTY"},{"x":16,"y":9,"isVisible":false,"type":"EMPTY"},{"x":16,"y":10,"isVisible":false,"type":"DECORATION1"},{"x":16,"y":11,"isVisible":false,"type":"EMPTY"},{"x":16,"y":12,"isVisible":false,"type":"EMPTY"},{"x":16,"y":13,"isVisible":false,"type":"EMPTY"},{"x":16,"y":14,"isVisible":false,"type":"EMPTY"},{"x":16,"y":15,"isVisible":false,"type":"EMPTY"},{"x":16,"y":16,"isVisible":false,"type":"EMPTY"},{"x":16,"y":17,"isVisible":false,"type":"EMPTY"},{"x":16,"y":18,"isVisible":false,"type":"EMPTY"},{"x":16,"y":19,"isVisible":false,"type":"EMPTY"}],[{"x":17,"y":0,"isVisible":false,"type":"EMPTY"},{"x":17,"y":1,"isVisible":false,"type":"WALL"},{"x":17,"y":2,"isVisible":false,"type":"WALL"},{"x":17,"y":3,"isVisible":false,"type":"FLOOR"},{"x":17,"y":4,"isVisible":false,"type":"WALL"},{"x":17,"y":5,"isVisible":false,"type":"WALL"},{"x":17,"y":6,"isVisible":false,"type":"WALL"},{"x":17,"y":7,"isVisible":false,"type":"WALL"},{"x":17,"y":8,"isVisible":false,"type":"WALL"},{"x":17,"y":9,"isVisible":false,"type":"EMPTY"},{"x":17,"y":10,"isVisible":false,"type":"EMPTY"},{"x":17,"y":11,"isVisible":false,"type":"WALL"},{"x":17,"y":12,"isVisible":false,"type":"WALL"},{"x":17,"y":13,"isVisible":false,"type":"WALL"},{"x":17,"y":14,"isVisible":false,"type":"WALL"},{"x":17,"y":15,"isVisible":false,"type":"WALL"},{"x":17,"y":16,"isVisible":false,"type":"WALL"},{"x":17,"y":17,"isVisible":false,"type":"WALL"},{"x":17,"y":18,"isVisible":false,"type":"WALL"},{"x":17,"y":19,"isVisible":false,"type":"WALL"}],[{"x":18,"y":0,"isVisible":false,"type":"DECORATION17"},{"x":18,"y":1,"isVisible":false,"type":"WALL"},{"x":18,"y":2,"isVisible":false,"type":"FLOOR"},{"x":18,"y":3,"isVisible":false,"type":"FLOOR"},{"x":18,"y":4,"isVisible":false,"type":"FLOOR"},{"x":18,"y":5,"isVisible":false,"type":"FLOOR"},{"x":18,"y":6,"isVisible":false,"type":"FLOOR"},{"x":18,"y":7,"isVisible":false,"type":"FLOOR"},{"x":18,"y":8,"isVisible":false,"type":"WALL"},{"x":18,"y":9,"isVisible":false,"type":"EMPTY"},{"x":18,"y":10,"isVisible":false,"type":"EMPTY"},{"x":18,"y":11,"isVisible":false,"type":"WALL"},{"x":18,"y":12,"isVisible":false,"type":"FLOOR"},{"x":18,"y":13,"isVisible":false,"type":"FLOOR"},{"x":18,"y":14,"isVisible":false,"type":"FLOOR"},{"x":18,"y":15,"isVisible":false,"type":"FLOOR"},{"x":18,"y":16,"isVisible":false,"type":"FLOOR"},{"x":18,"y":17,"isVisible":false,"type":"FLOOR","actor":{"canMove":false,"random":{"seed":155818683482541,"nextNextGaussian":0.0,"haveNextNextGaussian":false},"health":200,"attack":25,"defence":0}},{"x":18,"y":18,"isVisible":false,"type":"FLOOR"},{"x":18,"y":19,"isVisible":false,"type":"WALL"}],[{"x":19,"y":0,"isVisible":false,"type":"FLOOR"},{"x":19,"y":1,"isVisible":false,"type":"WALL"},{"x":19,"y":2,"isVisible":false,"type":"FLOOR"},{"x":19,"y":3,"isVisible":false,"type":"FLOOR"},{"x":19,"y":4,"isVisible":false,"type":"FLOOR"},{"x":19,"y":5,"isVisible":false,"type":"FLOOR"},{"x":19,"y":6,"isVisible":false,"type":"FLOOR"},{"x":19,"y":7,"isVisible":false,"type":"FLOOR"},{"x":19,"y":8,"isVisible":false,"type":"WALL"},{"x":19,"y":9,"isVisible":false,"type":"WALL"},{"x":19,"y":10,"isVisible":false,"type":"WALL"},{"x":19,"y":11,"isVisible":false,"type":"WALL"},{"x":19,"y":12,"isVisible":false,"type":"FLOOR"},{"x":19,"y":13,"isVisible":false,"type":"FLOOR"},{"x":19,"y":14,"isVisible":false,"type":"FLOOR"},{"x":19,"y":15,"isVisible":false,"type":"FLOOR","actor":{"random":{"seed":126093714863301,"nextNextGaussian":0.0,"haveNextNextGaussian":false},"health":40,"attack":5,"defence":0}},{"x":19,"y":16,"isVisible":false,"type":"FLOOR"},{"x":19,"y":17,"isVisible":false,"type":"FLOOR"},{"x":19,"y":18,"isVisible":false,"type":"FLOOR"},{"x":19,"y":19,"isVisible":false,"type":"WALL"}],[{"x":20,"y":0,"isVisible":false,"type":"EMPTY"},{"x":20,"y":1,"isVisible":false,"type":"WALL"},{"x":20,"y":2,"isVisible":false,"type":"FLOOR"},{"x":20,"y":3,"isVisible":false,"type":"FLOOR"},{"x":20,"y":4,"isVisible":false,"type":"FLOOR"},{"x":20,"y":5,"isVisible":false,"type":"FLOOR"},{"x":20,"y":6,"isVisible":false,"type":"FLOOR"},{"x":20,"y":7,"isVisible":false,"type":"FLOOR"},{"x":20,"y":8,"isVisible":false,"type":"FLOOR"},{"x":20,"y":9,"isVisible":false,"type":"FLOOR"},{"x":20,"y":10,"isVisible":false,"type":"FLOOR"},{"x":20,"y":11,"isVisible":false,"type":"FLOOR"},{"x":20,"y":12,"isVisible":false,"type":"FLOOR"},{"x":20,"y":13,"isVisible":false,"type":"FLOOR","actor":{"random":{"seed":129195725095381,"nextNextGaussian":0.0,"haveNextNextGaussian":false},"health":50,"attack":20,"defence":0}},{"x":20,"y":14,"isVisible":false,"type":"FLOOR"},{"x":20,"y":15,"isVisible":false,"type":"FLOOR","actor":{"random":{"seed":94456466955441,"nextNextGaussian":0.0,"haveNextNextGaussian":false},"health":50,"attack":1,"defence":10}},{"x":20,"y":16,"isVisible":false,"type":"FLOOR"},{"x":20,"y":17,"isVisible":false,"type":"FLOOR"},{"x":20,"y":18,"isVisible":false,"type":"FLOOR"},{"x":20,"y":19,"isVisible":false,"type":"WALL"}],[{"x":21,"y":0,"isVisible":false,"type":"EMPTY"},{"x":21,"y":1,"isVisible":false,"type":"WALL"},{"x":21,"y":2,"isVisible":false,"type":"FLOOR"},{"x":21,"y":3,"isVisible":false,"type":"FLOOR"},{"x":21,"y":4,"isVisible":false,"type":"FLOOR"},{"x":21,"y":5,"isVisible":false,"type":"FLOOR"},{"x":21,"y":6,"isVisible":false,"type":"FLOOR","actor":{"random":{"seed":128389640502081,"nextNextGaussian":0.0,"haveNextNextGaussian":false},"health":150,"attack":5,"defence":0}},{"x":21,"y":7,"isVisible":false,"type":"FLOOR"},{"x":21,"y":8,"isVisible":false,"type":"FLOOR"},{"x":21,"y":9,"isVisible":false,"type":"FLOOR"},{"x":21,"y":10,"isVisible":false,"type":"FLOOR"},{"x":21,"y":11,"isVisible":false,"type":"FLOOR"},{"x":21,"y":12,"isVisible":false,"type":"FLOOR"},{"x":21,"y":13,"isVisible":false,"type":"FLOOR","actor":{"random":{"seed":202046966804443,"nextNextGaussian":0.0,"haveNextNextGaussian":false},"health":30,"attack":20,"defence":5}},{"x":21,"y":14,"isVisible":false,"type":"FLOOR"},{"x":21,"y":15,"isVisible":false,"type":"FLOOR"},{"x":21,"y":16,"isVisible":false,"type":"FLOOR"},{"x":21,"y":17,"isVisible":false,"type":"FLOOR"},{"x":21,"y":18,"isVisible":false,"type":"STAIRS"},{"x":21,"y":19,"isVisible":false,"type":"WALL"}],[{"x":22,"y":0,"isVisible":false,"type":"EMPTY"},{"x":22,"y":1,"isVisible":false,"type":"WALL"},{"x":22,"y":2,"isVisible":false,"type":"FLOOR"},{"x":22,"y":3,"isVisible":false,"type":"FLOOR"},{"x":22,"y":4,"isVisible":false,"type":"FLOOR"},{"x":22,"y":5,"isVisible":false,"type":"FLOOR"},{"x":22,"y":6,"isVisible":false,"type":"FLOOR"},{"x":22,"y":7,"isVisible":false,"type":"FLOOR"},{"x":22,"y":8,"isVisible":false,"type":"WALL"},{"x":22,"y":9,"isVisible":false,"type":"WALL"},{"x":22,"y":10,"isVisible":false,"type":"WALL"},{"x":22,"y":11,"isVisible":false,"type":"WALL"},{"x":22,"y":12,"isVisible":false,"type":"FLOOR"},{"x":22,"y":13,"isVisible":false,"type":"FLOOR"},{"x":22,"y":14,"isVisible":false,"type":"FLOOR"},{"x":22,"y":15,"isVisible":false,"type":"FLOOR"},{"x":22,"y":16,"isVisible":false,"type":"FLOOR"},{"x":22,"y":17,"isVisible":false,"type":"FLOOR"},{"x":22,"y":18,"isVisible":false,"type":"FLOOR"},{"x":22,"y":19,"isVisible":false,"type":"WALL"}],[{"x":23,"y":0,"isVisible":false,"type":"EMPTY"},{"x":23,"y":1,"isVisible":false,"type":"WALL"},{"x":23,"y":2,"isVisible":false,"type":"FLOOR"},{"x":23,"y":3,"isVisible":false,"type":"FLOOR"},{"x":23,"y":4,"isVisible":false,"type":"FLOOR"},{"x":23,"y":5,"isVisible":false,"type":"FLOOR","actor":{"random":{"seed":256578342481265,"nextNextGaussian":0.0,"haveNextNextGaussian":false},"health":50,"attack":30,"defence":15}},{"x":23,"y":6,"isVisible":false,"type":"FLOOR"},{"x":23,"y":7,"isVisible":false,"type":"FLOOR"},{"x":23,"y":8,"isVisible":false,"type":"WALL"},{"x":23,"y":9,"isVisible":false,"type":"EMPTY"},{"x":23,"y":10,"isVisible":false,"type":"EMPTY"},{"x":23,"y":11,"isVisible":false,"type":"WALL"},{"x":23,"y":12,"isVisible":false,"type":"FLOOR"},{"x":23,"y":13,"isVisible":false,"type":"FLOOR"},{"x":23,"y":14,"isVisible":false,"type":"FLOOR"},{"x":23,"y":15,"isVisible":false,"type":"FLOOR"},{"x":23,"y":16,"isVisible":false,"type":"FLOOR"},{"x":23,"y":17,"isVisible":fa